min_db/__init__.py
min_db/connector.py
min_db/mapper.py
min_db/types.py
min_db-0.0.16.dist-info/METADATA
min_db-0.0.16.dist-info/WHEEL
min_db-0.0.16.dist-info/top_level.txt
min_db-0.0.16.dist-info/RECORD
