Metadata-Version: 2.1
Name: min-db
Version: 0.0.16
Summary: mybatis like minimum db utility
Author: kyon
Author-email: originky2@gmail.com
Classifier: Programming Language :: Python :: 3.11
Requires-Python: >=3.10
Requires-Dist: pydantic (>=2.7)
Requires-Dist: oracledb (>=1.4.2)
Requires-Dist: mysql-connector-python (>=8.2.0)
